{"note":"This file is an internal implementation detail to speed up HTML report generation. Its format can change at any time. You might be looking for the JSON report: https://coverage.rtfd.io/cmd.html#cmd-json","format":5,"version":"7.6.12","globals":"0bf072fe12f558866500da9f7d30d1b5","files":{"z_145eef247bfb46b6___init___py":{"hash":"db1ca38800b737f289e5a42ee916fb16","index":{"url":"z_145eef247bfb46b6___init___py.html","file":"src\\__init__.py","description":"","nums":{"precision":0,"n_files":1,"n_statements":1,"n_excluded":0,"n_missing":0,"n_branches":0,"n_partial_branches":0,"n_missing_branches":0}}},"z_145eef247bfb46b6_decorators_py":{"hash":"0915b1a9eb18f93f66cb49767ab35511","index":{"url":"z_145eef247bfb46b6_decorators_py.html","file":"src\\decorators.py","description":"","nums":{"precision":0,"n_files":1,"n_statements":19,"n_excluded":0,"n_missing":0,"n_branches":0,"n_partial_branches":0,"n_missing_branches":0}}},"z_145eef247bfb46b6_external_api_py":{"hash":"3691f31678a90f43bcd275a9846fbe52","index":{"url":"z_145eef247bfb46b6_external_api_py.html","file":"src\\external_api.py","description":"","nums":{"precision":0,"n_files":1,"n_statements":22,"n_excluded":0,"n_missing":0,"n_branches":0,"n_partial_branches":0,"n_missing_branches":0}}},"z_145eef247bfb46b6_generators_py":{"hash":"6d0a6c8942d73a7a3f4d03d79235e30c","index":{"url":"z_145eef247bfb46b6_generators_py.html","file":"src\\generators.py","description":"","nums":{"precision":0,"n_files":1,"n_statements":12,"n_excluded":0,"n_missing":0,"n_branches":0,"n_partial_branches":0,"n_missing_branches":0}}},"z_145eef247bfb46b6_masks_py":{"hash":"2c9f8c386afc5995b6d27ca60b36c140","index":{"url":"z_145eef247bfb46b6_masks_py.html","file":"src\\masks.py","description":"","nums":{"precision":0,"n_files":1,"n_statements":38,"n_excluded":0,"n_missing":6,"n_branches":0,"n_partial_branches":0,"n_missing_branches":0}}},"z_145eef247bfb46b6_processing_py":{"hash":"bcb32837e5a65c402f814310fdae1015","index":{"url":"z_145eef247bfb46b6_processing_py.html","file":"src\\processing.py","description":"","nums":{"precision":0,"n_files":1,"n_statements":17,"n_excluded":0,"n_missing":0,"n_branches":0,"n_partial_branches":0,"n_missing_branches":0}}},"z_145eef247bfb46b6_read_py":{"hash":"4569f18259cb6a97d85c383c7c574b88","index":{"url":"z_145eef247bfb46b6_read_py.html","file":"src\\read.py","description":"","nums":{"precision":0,"n_files":1,"n_statements":9,"n_excluded":0,"n_missing":0,"n_branches":0,"n_partial_branches":0,"n_missing_branches":0}}},"z_145eef247bfb46b6_utils_py":{"hash":"e52b4352bf797bf726ee7ef7351971b3","index":{"url":"z_145eef247bfb46b6_utils_py.html","file":"src\\utils.py","description":"","nums":{"precision":0,"n_files":1,"n_statements":17,"n_excluded":0,"n_missing":0,"n_branches":0,"n_partial_branches":0,"n_missing_branches":0}}},"z_145eef247bfb46b6_widget_py":{"hash":"960530ab980a33ef3559f1d83fc1b684","index":{"url":"z_145eef247bfb46b6_widget_py.html","file":"src\\widget.py","description":"","nums":{"precision":0,"n_files":1,"n_statements":14,"n_excluded":0,"n_missing":0,"n_branches":0,"n_partial_branches":0,"n_missing_branches":0}}}}}